hyo2.ssm2-2024.2.1-py3.11-nspkg.pth
hyo2/ssm2/__init__.py
hyo2/ssm2/app/__init__.py
hyo2/ssm2/app/gui/__init__.py
hyo2/ssm2/app/gui/soundspeedmanager/__init__.py
hyo2/ssm2/app/gui/soundspeedmanager/__main__.py
hyo2/ssm2/app/gui/soundspeedmanager/gui.py
hyo2/ssm2/app/gui/soundspeedmanager/mainwin.py
hyo2/ssm2/app/gui/soundspeedmanager/qt_callbacks.py
hyo2/ssm2/app/gui/soundspeedmanager/dialogs/__init__.py
hyo2/ssm2/app/gui/soundspeedmanager/dialogs/automate_dialog.py
hyo2/ssm2/app/gui/soundspeedmanager/dialogs/buttons_dialog.py
hyo2/ssm2/app/gui/soundspeedmanager/dialogs/common_metadata_dialog.py
hyo2/ssm2/app/gui/soundspeedmanager/dialogs/constant_gradient_profile_dialog.py
hyo2/ssm2/app/gui/soundspeedmanager/dialogs/dialog.py
hyo2/ssm2/app/gui/soundspeedmanager/dialogs/export_multi_profile_dialog.py
hyo2/ssm2/app/gui/soundspeedmanager/dialogs/export_profile_metadata_dialog.py
hyo2/ssm2/app/gui/soundspeedmanager/dialogs/export_profile_metadata_fields_dialog.py
hyo2/ssm2/app/gui/soundspeedmanager/dialogs/export_single_profile_dialog.py
hyo2/ssm2/app/gui/soundspeedmanager/dialogs/flaggable_input_dialog.py
hyo2/ssm2/app/gui/soundspeedmanager/dialogs/formatted_input_dialog.py
hyo2/ssm2/app/gui/soundspeedmanager/dialogs/import_data_dialog.py
hyo2/ssm2/app/gui/soundspeedmanager/dialogs/import_multi_profile_dialog.py
hyo2/ssm2/app/gui/soundspeedmanager/dialogs/import_single_profile_dialog.py
hyo2/ssm2/app/gui/soundspeedmanager/dialogs/metadata_dialog.py
hyo2/ssm2/app/gui/soundspeedmanager/dialogs/multi_selection_dialog.py
hyo2/ssm2/app/gui/soundspeedmanager/dialogs/output_folders_dialog.py
hyo2/ssm2/app/gui/soundspeedmanager/dialogs/plot_multi_profile_dialog.py
hyo2/ssm2/app/gui/soundspeedmanager/dialogs/plot_profiles_dialog.py
hyo2/ssm2/app/gui/soundspeedmanager/dialogs/proc_data_model.py
hyo2/ssm2/app/gui/soundspeedmanager/dialogs/project_new_dialog.py
hyo2/ssm2/app/gui/soundspeedmanager/dialogs/project_rename_dialog.py
hyo2.ssm2-2024.2.1.dist-info/AUTHORS.rst
hyo2.ssm2-2024.2.1.dist-info/LICENSE
hyo2.ssm2-2024.2.1.dist-info/METADATA
hyo2.ssm2-2024.2.1.dist-info/WHEEL
hyo2.ssm2-2024.2.1.dist-info/entry_points.txt
hyo2.ssm2-2024.2.1.dist-info/namespace_packages.txt
hyo2.ssm2-2024.2.1.dist-info/top_level.txt
hyo2.ssm2-2024.2.1.dist-info/RECORD
