Metadata-Version: 2.1
Name: hyo2.ssm2
Version: 2024.2.1
Summary: A library and an application to manage sound speed profiles.
Home-page: https://github.com/hydroffice/hyo2_soundspeed
Author: Giuseppe Masetti(UNH,JHC-CCOM); Barry Gallagher(NOAA,OCS); Chen Zhang(NOAA,OCS)
Author-email: gmasetti@ccom.unh.edu, barry.gallagher@noaa.gov, chen.zhang@noaa.gov
License: LGPLv2.1 or CCOM-UNH Industrial Associate license
Keywords: hydrography ocean mapping survey sound speed profiles
Classifier: Development Status :: 5 - Production/Stable
Classifier: Intended Audience :: Science/Research
Classifier: Natural Language :: English
Classifier: License :: OSI Approved :: GNU Lesser General Public License v2 or later (LGPLv2+)
Classifier: Operating System :: OS Independent
Classifier: Programming Language :: Python
Classifier: Programming Language :: Python :: 3
Classifier: Programming Language :: Python :: 3.11
Classifier: Programming Language :: Python :: 3.12
Classifier: Topic :: Scientific/Engineering :: GIS
Classifier: Topic :: Office/Business :: Office Suites
Requires-Python: >=3.11
License-File: LICENSE
License-File: AUTHORS.rst
Requires-Dist: hyo2.abc2 >=2.3.10
Requires-Dist: appdirs
Requires-Dist: cartopy
Requires-Dist: gsw
Requires-Dist: matplotlib
Requires-Dist: netCDF4
Requires-Dist: numpy <2.0.0
Requires-Dist: pillow
Requires-Dist: pyserial
Requires-Dist: PySide6
Requires-Dist: requests
Requires-Dist: scipy
